huscy_project/__init__.py
huscy_project/views.py
huscy_project/__pycache__/__init__.cpython-310.pyc
huscy_project/bin/__init__.py
huscy_project/bin/huscy.py
huscy_project/project_template/makefile
huscy_project/project_template/manage.py
huscy_project/project_template/config/asgi.py
huscy_project/project_template/config/settings.py
huscy_project/project_template/config/urls.py
huscy_project/project_template/config/wsgi.py
huscy_project/project_template/media/README.md
huscy_project/project_template/static/README.md
huscy_project/project_template/templates/index.html
huscy_project-0.9.2a31.dist-info/METADATA
huscy_project-0.9.2a31.dist-info/WHEEL
huscy_project-0.9.2a31.dist-info/entry_points.txt
huscy_project-0.9.2a31.dist-info/top_level.txt
huscy_project-0.9.2a31.dist-info/RECORD
