Metadata-Version: 2.1
Name: huscy-project
Version: 0.9.2a31
Summary: integration project for huscy apps
Author: Stefan Bunde
Author-email: stefanbunde+git@posteo.de
Requires-Dist: Django (>=4.2)
Provides-Extra: testing
Requires-Dist: tox ; extra == 'testing'
